quickpool/__init__.py
quickpool/py.typed
quickpool/quickpool.py
quickpool-2.2.0.dist-info/METADATA
quickpool-2.2.0.dist-info/WHEEL
quickpool-2.2.0.dist-info/licenses/LICENSE.txt
quickpool-2.2.0.dist-info/RECORD
