Metadata-Version: 2.4
Name: quickpool
Version: 2.2.0
Summary: Use ProcessPoolExecutor and ThreadPoolExecutor from concurrent.futures with a progress bar and less boilerplate.
Project-URL: Homepage, https://github.com/matt-manes/quickpool
Project-URL: Documentation, https://github.com/matt-manes/quickpool/tree/main/docs
Project-URL: Source code, https://github.com/matt-manes/quickpool/tree/main/src/quickpool
Author-email: Matt Manes <mattmanes@pm.me>
License-File: LICENSE.txt
Keywords: concurrent,futures,multiprocess,multithread
Classifier: License :: OSI Approved :: MIT License
Classifier: Operating System :: OS Independent
Classifier: Programming Language :: Python :: 3
Requires-Python: >=3.10
Requires-Dist: noiftimer
Requires-Dist: printbuddies
Requires-Dist: pytest
Requires-Dist: rich
